[
  {
    "character_class": "Bishop",
    "character_name": "Ayamushy",
    "equipments": [
      {
        "type": "Hat",
        "set": "Eternal",
        "name": null,
        "star_force": 18,
        "potentials": {
          "lines": [
            {
              "position": 1,
              "stat": "int",
              "value": 13
            },
            {
              "position": 2,
              "stat": "all_stats",
              "value": 7
            },
            {
              "position": 3,
              "stat": "all_stats",
              "value": 7
            }
          ],
          "total_stats": 30
        },
        "flames": {
          "main_stats": null,
          "secondary_stats": null,
          "att": null,
          "all_stats": null
        },
        "flame_score": 164,
        "preset_1": true,
        "preset_2": true,
        "preset_3": true,
        "equipped": true
      }
    ]
  },
  {
    "character_class": "Lara",
    "character_name": "HitsujiMayoi",
    "equipments": null
  },
  {
    "character_class": "Lynn",
    "character_name": "KawaiiBotan",
    "equipments": null
  },
  {
    "character_class": "Kanna",
    "character_name": "UmeTusugumi",
    "equipments": null
  },
  {
    "character_class": "Hayato",
    "character_name": "MomoHitomi",
    "equipments": null
  },
  {
    "character_class": "Bishop",
    "character_name": "NotAyamushy",
    "equipments": null
  },
  {
    "character_class": "Shade",
    "character_name": "EimiYuna",
    "equipments": null
  },
  {
    "character_class": "Phantom",
    "character_name": "KanamiYuuka",
    "equipments": null
  },
  {
    "character_class": "Mechanic",
    "character_name": "MekaMei",
    "equipments": null
  },
  {
    "character_class": "Arch Mage (I/L)",
    "character_name": "YukiRairi",
    "equipments": null
  },
  {
    "character_class": "Arch Mage (F/P)",
    "character_name": "MihoBusujima",
    "equipments": null
  },
  {
    "character_class": "Corsair",
    "character_name": "MakaneRimi",
    "equipments": null
  },
  {
    "character_class": "Kinesis",
    "character_name": "KuroyuriNen",
    "equipments": null
  },
  {
    "character_class": "Demon Avenger",
    "character_name": "YuuSayuri",
    "equipments": null
  },
  {
    "character_class": "Mercedes",
    "character_name": "YuukiMeru",
    "equipments": null
  },
  {
    "character_class": "Aran",
    "character_name": "NaramiChibi",
    "equipments": null
  },
  {
    "character_class": "Khali",
    "character_name": "KarinSatsuki",
    "equipments": null
  },
  {
    "character_class": "Adele",
    "character_name": "KurohaRiyuki",
    "equipments": null
  },
  {
    "character_class": "Bishop",
    "character_name": "FakeAyamushy",
    "equipments": null
  },
  {
    "character_class": "Zero",
    "character_name": "DeltaYuuki",
    "equipments": null
  },
  {
    "character_class": "Battle Mage",
    "character_name": "MeiKamakura",
    "equipments": null
  },
  {
    "character_class": "Luminous",
    "character_name": "MikageHikari",
    "equipments": null
  },
  {
    "character_class": "Illium",
    "character_name": "MiakiReiha",
    "equipments": null
  },
  {
    "character_class": "Blaze Wizard",
    "character_name": "AyakaEn",
    "equipments": null
  },
  {
    "character_class": "Marksman",
    "character_name": "ReiyaTooko",
    "equipments": null
  },
  {
    "character_class": "Night Lord",
    "character_name": "YozoraYomi",
    "equipments": null
  },
  {
    "character_class": "Wild Hunter",
    "character_name": "HayaRakko",
    "equipments": null
  },
  {
    "character_class": "Dark Knight",
    "character_name": "ToukoYamika",
    "equipments": null
  },
  {
    "character_class": "Bowmaster",
    "character_name": "RemiyaMisato",
    "equipments": null
  },
  {
    "character_class": "Angelic Buster",
    "character_name": "AtsukaNoeru",
    "equipments": null
  },
  {
    "character_class": "Evan",
    "character_name": "xRyuuka",
    "equipments": null
  },
  {
    "character_class": "Buccaneer",
    "character_name": "Amane​Hebi​"
  },
  {
    "character_class": "Paladin",
    "character_name": "RinKiyoe",
    "equipments": null
  },
  {
    "character_class": "Pathfinder",
    "character_name": "YukineYayoi",
    "equipments": null
  },
  {
    "character_class": "Shadower",
    "character_name": "MikageMiei",
    "equipments": null
  },
  {
    "character_class": "Cannonneer",
    "character_name": "HouryuuNuiko",
    "equipments": null
  },
  {
    "character_class": "Hero",
    "character_name": "TatewakiHime",
    "equipments": null
  },
  {
    "character_class": "Dual Blade",
    "character_name": "ReiniKuroha",
    "equipments": null
  },
  {
    "character_class": "Hoyoung",
    "character_name": "KoyamiSen",
    "equipments": null
  },
  {
    "character_class": "Xenon",
    "character_name": "YuranRenge",
    "equipments": null
  },
  {
    "character_class": "Ark",
    "character_name": "KouenYuri",
    "equipments": null
  },
  {
    "character_class": "Kain",
    "character_name": "KayaYamiya",
    "equipments": null
  },
  {
    "character_class": "Cadena",
    "character_name": "MegumiSeisa",
    "equipments": null
  },
  {
    "character_class": "Blaster",
    "character_name": "KanonHayame",
    "equipments": null
  },
  {
    "character_class": "Dawn Warrior",
    "character_name": "KyoukoRei",
    "equipments": null
  },
  {
    "character_class": "Demon Slayer",
    "character_name": "YamiOniyuri",
    "equipments": null
  },
  {
    "character_class": "Kaiser",
    "character_name": "RiyuTeruko",
    "equipments": null
  },
  {
    "character_class": "Mihile",
    "character_name": "KenshiKon",
    "equipments": null
  },
  {
    "character_class": "Night Walker",
    "character_name": "RiyoSetsuna",
    "equipments": null
  },
  {
    "character_class": "Thunder Breaker",
    "character_name": "AtsumiMirai",
    "equipments": null
  },
  {
    "character_class": "Wind Archer",
    "character_name": "FuyuAyane",
    "equipments": null
  }
]